toncenter/__init__.py
toncenter/client.py
toncenter/payment.py
toncenter/ticker.py
toncenter-0.0.5.dist-info/LICENSE
toncenter-0.0.5.dist-info/METADATA
toncenter-0.0.5.dist-info/WHEEL
toncenter-0.0.5.dist-info/top_level.txt
toncenter-0.0.5.dist-info/RECORD
