Metadata-Version: 2.1
Name: toncenter
Version: 0.0.5
Summary: Toncenter API Python3 async wrap.
Home-page: https://github.com/witer33/toncenter
Author: witer33
Author-email: dev@witer33.com
License: UNKNOWN
Project-URL: Bug Tracker, https://github.com/witer33/toncenter/issues
Platform: UNKNOWN
Classifier: Programming Language :: Python :: 3
Classifier: License :: OSI Approved :: GNU General Public License v3 (GPLv3)
Classifier: Operating System :: OS Independent
Requires-Python: >=3.6
License-File: LICENSE
